DICTIONARY
LICENCE.md
MANIFEST.in
README.md
setup.py
polysquare_generic_file_linter.egg-info/PKG-INFO
polysquare_generic_file_linter.egg-info/SOURCES.txt
polysquare_generic_file_linter.egg-info/dependency_links.txt
polysquare_generic_file_linter.egg-info/entry_points.txt
polysquare_generic_file_linter.egg-info/requires.txt
polysquare_generic_file_linter.egg-info/top_level.txt
polysquare_generic_file_linter.egg-info/zip-safe
polysquarelinter/__init__.py
polysquarelinter/cache_populate.py
polysquarelinter/en_US.txt
polysquarelinter/lint_spelling_only.py
polysquarelinter/linter.py
polysquarelinter/spelling.py
polysquarelinter/technical_words_dictionary.py
polysquarelinter/valid_words_dictionary.py
test/test_lint_spelling_only.py
test/test_linter_acceptance.py
test/test_spelling.py
test/test_warnings.py